Workbook

Sheet Práctica uno
A1: Manuel Enrique Báez Sanabria | B1: Estudiante
B3: =9*10 -> 90
A4: Articulo | B4: precio | C4: cantidad | D4: total
A5: PC | B5: 3000000 | C5: 2 | D5: =B5*C5 -> 6000000
A6: DD | B6: 85000 | C6: 4 | D6: =B6*C6 -> 340000
A7: RAM | B7: 60000 | C7: 3 | D7: =B7*C7 -> 180000

Sheet Planilla
A1: I Trimestre | B1: Empresa Comercial SA
B2: 2019
B3: Nombre | C3: Salario Por Hora | D3: Horas de Trabajo | E3: Salario | F3: CCSS 9% | G3: Banco Popular 5% | H3: JUPEMA 7% | I3: Salario Neto | J3: Condición
B4: Cristian Chavez | C4: 6500 | D4: 66 | E4: =C4*D4 -> 429000 | F4: =E4*9% -> 38610 | G4: =E4*5% -> 21450 | H4: =E4*7% -> 30030 | I4: =E4-F4-G4-H4 -> 338910 | J4: =IF(I4>=1000000,"Clase A",IF(I4>500000,"Clase B","Clase C")) -> Clase C
B5: Federico Comez | C5: 20000 | D5: 98 | E5: =C5*D5 -> 1960000 | F5: =E5*9% -> 176400 | G5: =E5*5% -> 98000 | H5: =E5*7% -> 137200 | I5: =E5-F5-G5-H5 -> 1548400 | J5: =IF(I5>=1000000,"Clase A",IF(I5>500000,"Clase B","Clase C")) -> Clase A
B6: John Alvarado | C6: 5000 | D6: 50 | E6: =C6*D6 -> 250000 | F6: =E6*9% -> 22500 | G6: =E6*5% -> 12500 | H6: =E6*7% -> 17500 | I6: =E6-F6-G6-H6 -> 197500 | J6: =IF(I6>=1000000,"Clase A",IF(I6>500000,"Clase B","Clase C")) -> Clase C
B7: Max Chacón | C7: 10000 | D7: 90 | E7: =C7*D7 -> 900000 | F7: =E7*9% -> 81000 | G7: =E7*5% -> 45000 | H7: =E7*7% -> 63000 | I7: =E7-F7-G7-H7 -> 711000 | J7: =IF(I7>=1000000,"Clase A",IF(I7>500000,"Clase B","Clase C")) -> Clase B
B8: Félix Mora | C8: 25000 | D8: 65 | E8: =D8*C8 -> 1625000 | F8: =E8*9% -> 146250 | G8: =E8*5% -> 81250 | H8: =E8*7% -> 113750 | I8: =E8-F8-G8-H8 -> 1283750 | J8: =IF(I8>=1000000,"Clase A",IF(I8>500000,"Clase B","Clase C")) -> Clase A
B9: Sam Fernanadez | C9: 15000 | D9: 54 | E9: =C9*D9 -> 810000 | F9: =E9*9% -> 72900 | G9: =E9*5% -> 40500 | H9: =E9*7% -> 56700 | I9: =E9-F9-G9-H9 -> 639900 | J9: =IF(I9>=1000000,"Clase A",IF(I9>500000,"Clase B","Clase C")) -> Clase B
B10: James Arias | C10: 8000 | D10: 46 | E10: =C10*D10 -> 368000 | F10: =E10*9% -> 33120 | G10: =E10*5% -> 18400 | H10: =E10*7% -> 25760 | I10: =E10-F10-G10-H10 -> 290720 | J10: =IF(I10>=1000000,"Clase A",IF(I10>500000,"Clase B","Clase C")) -> Clase C
B11: Sergio Hernandez | C11: 10050 | D11: 78 | E11: =C11*D11 -> 783900 | F11: =E11*9% -> 70551 | G11: =E11*5% -> 39195 | H11: =E11*7% -> 54873 | I11: =E11-F11-G11-H11 -> 619281 | J11: =IF(I11>=1000000,"Clase A",IF(I11>500000,"Clase B","Clase C")) -> Clase B
B12: Rosibel Garcia | C12: 8700 | D12: 96 | E12: =C12*D12 -> 835200 | F12: =E12*9% -> 75168 | G12: =E12*5% -> 41760 | H12: =E12*7% -> 58464 | I12: =E12-F12-G12-H12 -> 659808 | J12: =IF(I12>=1000000,"Clase A",IF(I12>500000,"Clase B","Clase C")) -> Clase B
B13: Percy Corrales | C13: 2000 | D13: 48 | E13: =C13*D13 -> 96000 | F13: =E13*9% -> 8640 | G13: =E13*5% -> 4800 | H13: =E13*7% -> 6720 | I13: =E13-F13-G13-H13 -> 75840 | J13: =IF(I13>=1000000,"Clase A",IF(I13>500000,"Clase B","Clase C")) -> Clase C
B14: Total de empleados | C14: =COUNTA(B4:B13) -> 10
B15: Salario Neto Mayor | C15: =MAX(I4:I13) -> 1548400
B16: Salario Neto Menor | C16: =MIN(I4:I13) -> 75840
B17: Sal Netos>450000 | C17: =COUNTIF(I4:I13,">450000") -> 6
B18: Total Clase A | C18: =COUNTIF(I4:I13,">=1000000") -> 2
B19: Total Clase B | C19: =COUNTIF(J4:J13,"Clase B") -> 4
B20: Total Clase C | C20: =COUNTIF(I4:I13,"<500000") -> 4

Sheet Precios Productos
A1: Código | B1: Artículos | C1: Marca | D1: Precio Compra | E1: Impuesto Porcentual | F1: Impuesto | G1: Precio de Venta
A2: 1205 | B2: Celular | C2: LG | D2: 200000 | E2: =IF(D2>=800000,"16%",IF(D2>=500000,"12%",IF(D2>=200000, "8%","4%"))) -> 8% | F2: =IF(D2>=800000,D2*16%,IF(D2>=500000,D2*12%,IF(D2>=200000, D2*8%,D2*4%))) -> 16000 | G2: =+D2+F2 -> 216000
A3: 1287 | B3: Lava Platos | C3: Frigerade | D3: 500000 | E3: =IF(D3>=800000,"16%",IF(D3>=500000,"12%",IF(D3>=200000, "8%","4%"))) -> 12% | F3: =IF(D3>=800000,D3*16%,IF(D3>=500000,D3*12%,IF(D3>=200000, D3*8%,D3*4%))) -> 60000 | G3: =+D3+F3 -> 560000
A4: 1548 | B4: Plancha | C4: Oster | D4: 20000 | E4: =IF(D4>=800000,"16%",IF(D4>=500000,"12%",IF(D4>=200000, "8%","4%"))) -> 4% | F4: =IF(D4>=800000,D4*16%,IF(D4>=500000,D4*12%,IF(D4>=200000, D4*8%,D4*4%))) -> 800 | G4: =+D4+F4 -> 20800
A5: 2541 | B5: Lavadora | C5: Whirpool | D5: 600000 | E5: =IF(D5>=800000,"16%",IF(D5>=500000,"12%",IF(D5>=200000, "8%","4%"))) -> 12% | F5: =IF(D5>=800000,D5*16%,IF(D5>=500000,D5*12%,IF(D5>=200000, D5*8%,D5*4%))) -> 72000 | G5: =+D5+F5 -> 672000
A6: 5545 | B6: Desktop | C6: HP | D6: 900000 | E6: =IF(D6>=800000,"16%",IF(D6>=500000,"12%",IF(D6>=200000, "8%","4%"))) -> 16% | F6: =IF(D6>=800000,D6*16%,IF(D6>=500000,D6*12%,IF(D6>=200000, D6*8%,D6*4%))) -> 144000 | G6: =+D6+F6 -> 1044000
A7: 5645 | B7: Celular | C7: Apple | D7: 400000 | E7: =IF(D7>=800000,"16%",IF(D7>=500000,"12%",IF(D7>=200000, "8%","4%"))) -> 8% | F7: =IF(D7>=800000,D7*16%,IF(D7>=500000,D7*12%,IF(D7>=200000, D7*8%,D7*4%))) -> 32000 | G7: =+D7+F7 -> 432000
A8: 6321 | B8: Laptop | C8: Dell | D8: 300000 | E8: =IF(D8>=800000,"16%",IF(D8>=500000,"12%",IF(D8>=200000, "8%","4%"))) -> 8% | F8: =IF(D8>=800000,D8*16%,IF(D8>=500000,D8*12%,IF(D8>=200000, D8*8%,D8*4%))) -> 24000 | G8: =+D8+F8 -> 324000
A9: 6697 | B9: PS4 | C9: Sony | D9: 275000 | E9: =IF(D9>=800000,"16%",IF(D9>=500000,"12%",IF(D9>=200000, "8%","4%"))) -> 8% | F9: =IF(D9>=800000,D9*16%,IF(D9>=500000,D9*12%,IF(D9>=200000, D9*8%,D9*4%))) -> 22000 | G9: =+D9+F9 -> 297000
A10: 8895 | B10: Cocina | C10: Mabe | D10: 750000 | E10: =IF(D10>=800000,"16%",IF(D10>=500000,"12%",IF(D10>=200000, "8%","4%"))) -> 12% | F10: =IF(D10>=800000,D10*16%,IF(D10>=500000,D10*12%,IF(D10>=200000, D10*8%,D10*4%))) -> 90000 | G10: =+D10+F10 -> 840000
A11: 9874 | B11: Tablet | C11: AOC | D11: 100000 | E11: =IF(D11>=800000,"16%",IF(D11>=500000,"12%",IF(D11>=200000, "8%","4%"))) -> 4% | F11: =IF(D11>=800000,D11*16%,IF(D11>=500000,D11*12%,IF(D11>=200000, D11*8%,D11*4%))) -> 4000 | G11: =+D11+F11 -> 104000

Sheet Búsqueda
A1: Código | B1: 5545
A2: Artículo | B2: Precio de compra | C2: Precio de venta
A3: =LOOKUP(B1,'Precios Productos'!A2:A11,'Precios Productos'!B2:B11) -> Desktop

Sheet Factura
A1: # | B1: Código | C1: Articulo | D1: Marca | E1: Precio de Venta | F1: Cantidad | G1: Valor
A2: 1 | B2: 1287 | C2: =LOOKUP(B2,'Precios Productos'!A2:A11,'Precios Productos'!B2:B11) -> Lava Platos | D2: =LOOKUP(B2,'Precios Productos'!A2:A11,'Precios Productos'!C2:C11) -> Frigerade | E2: =LOOKUP(B2,'Precios Productos'!A2:A11,'Precios Productos'!G2:G11) -> 560000 | F2: 4 | G2: =E2*F2 -> 2240000
A3: 2 | B3: 5545 | C3: =LOOKUP(B3,'Precios Productos'!A2:A11,'Precios Productos'!B2:B11) -> Desktop | D3: =LOOKUP(B3,'Precios Productos'!A2:A11,'Precios Productos'!C2:C11) -> HP | E3: =LOOKUP(B3,'Precios Productos'!A2:A11,'Precios Productos'!G2:G11) -> 1044000 | F3: 2 | G3: =E3*F3 -> 2088000
A4: 3 | B4: 1205 | C4: =LOOKUP(B4,'Precios Productos'!A2:A11,'Precios Productos'!B2:B11) -> Celular | D4: =LOOKUP(B4,'Precios Productos'!A2:A11,'Precios Productos'!C2:C11) -> LG | E4: =LOOKUP(B4,'Precios Productos'!A2:A11,'Precios Productos'!G2:G11) -> 216000 | F4: 4 | G4: =E4*F4 -> 864000
A5: 4 | B5: 9887 | C5: =LOOKUP(B5,'Precios Productos'!A2:A11,'Precios Productos'!B2:B11) -> Tablet | D5: =LOOKUP(B5,'Precios Productos'!A2:A11,'Precios Productos'!C2:C11) -> AOC | E5: =LOOKUP(B5,'Precios Productos'!A2:A11,'Precios Productos'!G2:G11) -> 104000 | F5: 2 | G5: =E5*F5 -> 208000
A6: 5 | G6: =E6*F6 -> 0
A7: 6 | G7: =E7*F7 -> 0
A8: 7 | G8: =E8*F8 -> 0
A9: 8 | G9: =E9*F9 -> 0
A10: 9 | G10: =E10*F10 -> 0
A11: 10 | G11: =E11*F11 -> 0
F13: Subtotal | G13: =SUM(G2:G5) -> 5400000
F14: Subtotal con IV | G14: =G13+(G13*5%) -> 5670000
F15: IV 5% | G15: =G13*5% -> 270000
F16: Descuento | G16: =IF(G14>1000000,(G14*8%),IF(G14>=500000,(G14*5%),IF(G14<50000,(G14*2%)))) -> 453600
F17: Descuento Porcentual | G17: =IF(G14>1000000,"8%",IF(G14>=500000,"5%",IF(G14<50000,"2%"))) -> 8%
F18: Total | G18: =IF(G14>1000000,G14-(G14*8%),IF(G14>=500000,G14-(G14*5%),IF(G14<50000,G14-(G14*2%)))) -> 5216400
O26: 874

Sheet Marcadores
A1: Equipo Local | B1: Equipo Visitante | C1: Marcador | E1: Ganadores | F1: Calculos | G1: Diferencia | H1: Perdedores | I1: Empate
A2: Limón | B2: Cartagines | C2: 7 | D2: 8 | E2: =IF(C2=D2,"",IF(C2>D2,A2,B2)) -> Cartagines | F2: =IF(C2=D2,"0",IF(D2>C2,C2-D2,D2-C2)) -> -1 | G2: =IF(C2=D2,"0",IF(D2>C2,D2-C2,C2-D2)) -> 1 | H2: =IF(C2=D2,"", IF(C2>D2,B2,A2)) -> Limón | I2: =IF(C2=D2,A2,"") | J2: =IF(C2=D2,B2,"")
A3: Alajuela | B3: Carmelita | C3: 3 | D3: 2 | E3: =IF(C3=D3,"",IF(C3>D3,A3,B3)) -> Alajuela | F3: =IF(C3=D3,"0",IF(D3>C3,C3-D3,D3-C3)) -> -1 | G3: =IF(C3=D3,"0",IF(D3>C3,D3-C3,C3-D3)) -> 1 | H3: =IF(C3=D3,"", IF(C3>D3,B3,A3)) -> Carmelita | I3: =IF(C3=D3,A3,"") | J3: =IF(C3=D3,B3,"")
A4: Heredia | B4: UCR | C4: 3 | D4: 3 | E4: =IF(C4=D4,"",IF(C4>D4,A4,B4)) | F4: =IF(C4=D4,"0",IF(D4>C4,C4-D4,D4-C4)) -> 0 | G4: =IF(C4=D4,"0",IF(D4>C4,D4-C4,C4-D4)) -> 0 | H4: =IF(C4=D4,"", IF(C4>D4,B4,A4)) | I4: =IF(C4=D4,A4,"") -> Heredia | J4: =IF(C4=D4,B4,"") -> UCR
A5: San Carlos | B5: Saprissa | C5: 4 | D5: 4 | E5: =IF(C5=D5,"",IF(C5>D5,A5,B5)) | F5: =IF(C5=D5,"0",IF(D5>C5,C5-D5,D5-C5)) -> 0 | G5: =IF(C5=D5,"0",IF(D5>C5,D5-C5,C5-D5)) -> 0 | H5: =IF(C5=D5,"", IF(C5>D5,B5,A5)) | I5: =IF(C5=D5,A5,"") -> San Carlos | J5: =IF(C5=D5,B5,"") -> Saprissa
B9: I Trim | C9: II Trim | D9: III Trim | E9: Condición
B10: 91 | C10: 91 | D10: 91 | E10: =IF(AND(B10>=90,C10>=90,D10>=90),"Eximido","NO eximido") -> Eximido

Sheet Gato
E1: Jugador X | F1: =IF(OR(AND(A1="X",B1="X",C1="X"),AND(A1="X",A2="X",A3="X"),AND(B1="X",B2="X",B3="X"),AND(C1="X",C2="X",C3="X"),AND(A1="X",B2="X",C3="X"),AND(C1="X",B2="X",A3="X"),AND(A2="X",B2="X",C2="X"),AND(A3="X",B3="X",C3="X")),"Ganador","")
E2: Jugador O | F2: =IF(OR(AND(A1="O",B1="O",C1="O"),AND(A1="O",A2="O",A3="O"),AND(B1="O",B2="O",B3="O"),AND(C1="O",C2="O",C3="O"),AND(A1="O",B2="O",C3="O"),AND(C1="O",B2="O",A3="O"),AND(A2="O",B2="O",C2="O"),AND(A3="O",B3="O",C3="O")),"Ganador","")
D3: =COUNTA(A1,B1,C1,A2,B2,C2,A3,B3,C3) -> 0 | E3: =IF(AND(D3=9,F1="",F2=""),"Empate","")

Sheet Tabla Informatica
B2: Ficha Docente
B3: Cedula | C3: 115490622
B4: Nombre | C4: =LOOKUP(C3,Docentes!B3:B12,Docentes!C3:C12) -> Pablo Alvarado
B5: Sal X Leccion | C5: =LOOKUP(C3,Docentes!B3:B12,Docentes!F3:F12) -> 15000 | D5: Grado Academico | E5: =LOOKUP(C3,Docentes!B3:B12,Docentes!E3:E12) -> Licenciado
B6: Sal Base | C6: =LOOKUP(C3,Docentes!B3:B12,Docentes!G3:G12) -> 750000 | D6: # De Lecciones | E6: =LOOKUP(C3,Docentes!B3:B12,Docentes!D3:D12) -> 50
B7: Ande | C7: =LOOKUP(C3,Docentes!B3:B12,Docentes!H3:H12) -> 37500 | D7: Sal Neto | E7: =LOOKUP(C3,Docentes!B3:B12,Docentes!J3:J12) -> 615000
B8: CCSS | C8: =LOOKUP(C3,Docentes!B3:B12,Docentes!I3:I12) -> 97500 | K8: 115490622
K9: 109485765
K10: 109110681
K11: 145806980
K12: 147089036
K13: 175849603
K14: 164525301
K15: 154876123
K16: 102545875
K17: 102654839

Sheet Horarios
A1: Jueves | B1: Viernes | C1: Sábado | D1: Domingo | E1: Lunes | F1: Martes | G1: Miércoles | H1: Jueves
A2: 43510 | B2: 43511 | C2: 43512 | D2: 43513 | E2: 43514 | F2: 43515 | G2: 43516 | H2: 43517
A4: Jueves | B4: Jueves | C4: Jueves | D4: Jueves | E4: Jueves | F4: Jueves | G4: Jueves | H4: Jueves
A5: 43510 | B5: =A5+7 -> 43517 | C5: =B5+7 -> 43524 | D5: =C5+7 -> 43531 | E5: =D5+7 -> 43538 | F5: =E5+7 -> 43545 | G5: =F5+7 -> 43552 | H5: =G5+7 -> 43559

Sheet Docentes
A2: # | B2: Cedula | C2: Nombre | D2: # De Lecciones | E2: Grado Academico | F2: Sal x Leccion | G2: Sal Base | H2: ANDE 5% | I2: CCSS 13% | J2: Sal Neto
A3: 1 | B3: 102545875 | C3: Rosa Sanchez | D3: 15 | E3: =IF(D3>=40,"Licenciado",IF(D3>=30,"Bachiller",IF(D3>=10,"Diplomado","Aspirante"))) -> Diplomado | F3: =IF(E3="Licenciado",15000,IF(E3="Bachiller",10000,IF(E3="Diplomado", 5000,3000))) -> 5000 | G3: =D3*F3 -> 75000 | H3: =G3*5% -> 3750 | I3: =G3*13% -> 9750 | J3: =G3-H3-I3 -> 61500
A4: 2 | B4: 102654839 | C4: Fernando Del Castillo | D4: 60 | E4: =IF(D4>=40,"Licenciado",IF(D4>=30,"Bachiller",IF(D4>=10,"Diplomado","Aspirante"))) -> Licenciado | F4: =IF(E4="Licenciado",15000,IF(E4="Bachiller",10000,IF(E4="Diplomado", 5000,3000))) -> 15000 | G4: =D4*F4 -> 900000 | H4: =G4*5% -> 45000 | I4: =G4*13% -> 117000 | J4: =G4-H4-I4 -> 738000
A5: 3 | B5: 109110681 | C5: Elias Carmona | D5: 6 | E5: =IF(D5>=40,"Licenciado",IF(D5>=30,"Bachiller",IF(D5>=10,"Diplomado","Aspirante"))) -> Aspirante | F5: =IF(E5="Licenciado",15000,IF(E5="Bachiller",10000,IF(E5="Diplomado", 5000,3000))) -> 3000 | G5: =D5*F5 -> 18000 | H5: =G5*5% -> 900 | I5: =G5*13% -> 2340 | J5: =G5-H5-I5 -> 14760
A6: 4 | B6: 109485765 | C6: Nestor Cruz | D6: 51 | E6: =IF(D6>=40,"Licenciado",IF(D6>=30,"Bachiller",IF(D6>=10,"Diplomado","Aspirante"))) -> Licenciado | F6: =IF(E6="Licenciado",15000,IF(E6="Bachiller",10000,IF(E6="Diplomado", 5000,3000))) -> 15000 | G6: =D6*F6 -> 765000 | H6: =G6*5% -> 38250 | I6: =G6*13% -> 99450 | J6: =G6-H6-I6 -> 627300
A7: 5 | B7: 115490622 | C7: Pablo Alvarado | D7: 50 | E7: =IF(D7>=40,"Licenciado",IF(D7>=30,"Bachiller",IF(D7>=10,"Diplomado","Aspirante"))) -> Licenciado | F7: =IF(E7="Licenciado",15000,IF(E7="Bachiller",10000,IF(E7="Diplomado", 5000,3000))) -> 15000 | G7: =D7*F7 -> 750000 | H7: =G7*5% -> 37500 | I7: =G7*13% -> 97500 | J7: =G7-H7-I7 -> 615000
A8: 6 | B8: 145806980 | C8: Juan Araya | D8: 10 | E8: =IF(D8>=40,"Licenciado",IF(D8>=30,"Bachiller",IF(D8>=10,"Diplomado","Aspirante"))) -> Diplomado | F8: =IF(E8="Licenciado",15000,IF(E8="Bachiller",10000,IF(E8="Diplomado", 5000,3000))) -> 5000 | G8: =D8*F8 -> 50000 | H8: =G8*5% -> 2500 | I8: =G8*13% -> 6500 | J8: =G8-H8-I8 -> 41000
A9: 7 | B9: 147089036 | C9: Randall Jimenez | D9: 24 | E9: =IF(D9>=40,"Licenciado",IF(D9>=30,"Bachiller",IF(D9>=10,"Diplomado","Aspirante"))) -> Diplomado | F9: =IF(E9="Licenciado",15000,IF(E9="Bachiller",10000,IF(E9="Diplomado", 5000,3000))) -> 5000 | G9: =D9*F9 -> 120000 | H9: =G9*5% -> 6000 | I9: =G9*13% -> 15600 | J9: =G9-H9-I9 -> 98400
A10: 8 | B10: 154876123 | C10: Ignacio Abarca | D10: 32 | E10: =IF(D10>=40,"Licenciado",IF(D10>=30,"Bachiller",IF(D10>=10,"Diplomado","Aspirante"))) -> Bachiller | F10: =IF(E10="Licenciado",15000,IF(E10="Bachiller",10000,IF(E10="Diplomado", 5000,3000))) -> 10000 | G10: =D10*F10 -> 320000 | H10: =G10*5% -> 16000 | I10: =G10*13% -> 41600 | J10: =G10-H10-I10 -> 262400
A11: 9 | B11: 164525301 | C11: Filiberto Martinez | D11: 8 | E11: =IF(D11>=40,"Licenciado",IF(D11>=30,"Bachiller",IF(D11>=10,"Diplomado","Aspirante"))) -> Aspirante | F11: =IF(E11="Licenciado",15000,IF(E11="Bachiller",10000,IF(E11="Diplomado", 5000,3000))) -> 3000 | G11: =D11*F11 -> 24000 | H11: =G11*5% -> 1200 | I11: =G11*13% -> 3120 | J11: =G11-H11-I11 -> 19680
A12: 10 | B12: 175849603 | C12: Alejo Barejo | D12: 36 | E12: =IF(D12>=40,"Licenciado",IF(D12>=30,"Bachiller",IF(D12>=10,"Diplomado","Aspirante"))) -> Bachiller | F12: =IF(E12="Licenciado",15000,IF(E12="Bachiller",10000,IF(E12="Diplomado", 5000,3000))) -> 10000 | G12: =D12*F12 -> 360000 | H12: =G12*5% -> 18000 | I12: =G12*13% -> 46800 | J12: =G12-H12-I12 -> 295200
B14: Salario Neto Mayor | C14: =MAX(J3:J12) -> 738000
B15: Salario Neto Menor | C15: =MIN(J3:J12) -> 14760
B16: S Neto Mayor A 500000 | C16: =COUNTIF(J3:J12,">500000") -> 3
B17: Total De Bachiller | C17: =COUNTIF(E3:E12,"Bachiller") -> 2
B18: Total De Aspirantes | C18: =COUNTIF(E3:E12,"Aspirante") -> 2

Sheet Evaluación
A1: INFO DESARROLLO | B1: CEDES DON BOSCO
B2: III Trimestre
B3: Estudiante | C3: I Trimestre | D3: II Trimestre | E3: III Trimestre | F3: Anual | G3: Condición
B4: Leonardo Aguilar | C4: 64 | D4: 13 | E4: 100 | F4: =(C4+D4+E4)/3 -> 59 | G4: =IF(F4>=70,"Aprobado",IF(F4>=50,"Aplazado","Reprobado")) -> Aplazado
B5: Federico Garcia | C5: 84 | D5: 89 | E5: 85 | F5: =(C5+D5+E5)/3 -> 86 | G5: =IF(F5>=70,"Aprobado",IF(F5>=50,"Aplazado","Reprobado")) -> Aprobado
B6: Alfonso Paniagua | C6: 40 | D6: 71 | E6: 96 | F6: =(C6+D6+E6)/3 -> 69 | G6: =IF(F6>=70,"Aprobado",IF(F6>=50,"Aplazado","Reprobado")) -> Aplazado
B7: Reinaldo Carmona | C7: 87 | D7: 88 | E7: 86 | F7: =(C7+D7+E7)/3 -> 87 | G7: =IF(F7>=70,"Aprobado",IF(F7>=50,"Aplazado","Reprobado")) -> Aprobado
B8: James Cordoba | C8: 91 | D8: 91 | E8: 91 | F8: =(C8+D8+E8)/3 -> 91 | G8: =IF(F8>=70,"Aprobado",IF(F8>=50,"Aplazado","Reprobado")) -> Aprobado
B9: Francisco Jimenez | C9: 83 | D9: 84 | E9: 82 | F9: =(C9+D9+E9)/3 -> 83 | G9: =IF(F9>=70,"Aprobado",IF(F9>=50,"Aplazado","Reprobado")) -> Aprobado
B10: Johnathan Rodriguez | C10: 25 | D10: 100 | E10: 10 | F10: =(C10+D10+E10)/3 -> 45 | G10: =IF(F10>=70,"Aprobado",IF(F10>=50,"Aplazado","Reprobado")) -> Reprobado
B11: Miguel Mora | C11: 68 | D11: 100 | E11: 90 | F11: =(C11+D11+E11)/3 -> 86 | G11: =IF(F11>=70,"Aprobado",IF(F11>=50,"Aplazado","Reprobado")) -> Aprobado
B12: George Azofeifa | C12: 50 | D12: 87 | E12: 73 | F12: =(C12+D12+E12)/3 -> 70 | G12: =IF(F12>=70,"Aprobado",IF(F12>=50,"Aplazado","Reprobado")) -> Aprobado
B13: Paco Fernandez | C13: 97 | D13: 100 | E13: 100 | F13: =(C13+D13+E13)/3 -> 99 | G13: =IF(F13>=70,"Aprobado",IF(F13>=50,"Aplazado","Reprobado")) -> Aprobado
B14: Cantidad de Estudiantes | C14: =COUNTA(B4:B13) -> 10
B15: Anual Mayor | C15: =MAX(F4:F13) -> 99
B16: Anual Menor | C16: =MIN(F4:F13) -> 45
B17: Anuales >85 | C17: =COUNTIF(F4:F13,">85") -> 5
B18: Total de aprobados | C18: =COUNTIF(F4:F13,">=70") -> 7
B19: Total de aplazados | C19: =COUNTIF(G4:G13,"Aplazado") -> 2
B20: Total de reprobados | C20: =COUNTIF(F4:F13,"<50") -> 1
