Workbook

Sheet Planilla
B2: La Pozuelo
B3: Nombre Completo | C3: Salario Base | D3: CCSS 11% | E3: Asoc 5% | F3: Banco 4% | G3: Salario | H3: Condición
B4: Paco Fernandez | C4: 5000000 | D4: =C4*11% -> 550000 | E4: =C4*5% -> 250000 | F4: =C4*4% -> 200000 | G4: =C4-D4-E4-F4 -> 4000000 | H4: =IF(G4>1000000,"Clase A",IF(G4>=600000,"Clase B",IF(G4>=100000,"Clase C","Clase D"))) -> Clase A
B5: Lucas Jimenez | C5: 750000 | D5: =C5*11% -> 82500 | E5: =C5*5% -> 37500 | F5: =C5*4% -> 30000 | G5: =C5-D5-E5-F5 -> 600000 | H5: =IF(G5>1000000,"Clase A",IF(G5>=600000,"Clase B",IF(G5>=100000,"Clase C","Clase D"))) -> Clase B
B6: Lizbeth Aragones | C6: 352000 | D6: =C6*11% -> 38720 | E6: =C6*5% -> 17600 | F6: =C6*4% -> 14080 | G6: =C6-D6-E6-F6 -> 281600 | H6: =IF(G6>1000000,"Clase A",IF(G6>=600000,"Clase B",IF(G6>=100000,"Clase C","Clase D"))) -> Clase C
B7: Guillermo Rodriguez | C7: 15200 | D7: =C7*11% -> 1672 | E7: =C7*5% -> 760 | F7: =C7*4% -> 608 | G7: =C7-D7-E7-F7 -> 12160 | H7: =IF(G7>1000000,"Clase A",IF(G7>=600000,"Clase B",IF(G7>=100000,"Clase C","Clase D"))) -> Clase D
B8: Fernando Brenes | C8: 654000 | D8: =C8*11% -> 71940 | E8: =C8*5% -> 32700 | F8: =C8*4% -> 26160 | G8: =C8-D8-E8-F8 -> 523200 | H8: =IF(G8>1000000,"Clase A",IF(G8>=600000,"Clase B",IF(G8>=100000,"Clase C","Clase D"))) -> Clase C
B9: Total de empleados | C9: =COUNTA(B4,B5,B6,B7,B8) -> 5
B10: Salario Minimo | C10: =MIN(G4:G8) -> 12160
B11: Salario Máximo | C11: =MAX(G4:G8) -> 4000000
B12: Total de salarios mayores que 220000 | C12: =COUNTIF(G4:G8,">220000") -> 4
B13: Total Clase A | C13: =COUNTIF(G4:G8,">=1000000") -> 1
B14: Total Clase B | C14: =COUNTIF(H4:H8,"Clase B") -> 1

Sheet Productos
B2: Código | C2: Articulo | D2: Marca | E2: Precio Compra | F2: Aranceles 11% | G2: Impuesto Nacional 8% | H2: Categoría | I2: Precio Venta
B3: 1121 | C3: Laptop | D3: Lenovo | E3: 450000 | F3: =E3*11% -> 49500 | G3: =E3*5% -> 22500 | H3: =IF(E3>300000,"Nuevo","De Segunda") -> Nuevo | I3: =E3+F3+G3 -> 522000
B4: 1912 | C4: Celular | D4: Huawei | E4: 142000 | F4: =E4*11% -> 15620 | G4: =E4*5% -> 7100 | H4: =IF(E4>300000,"Nuevo","De Segunda") -> De Segunda | I4: =E4+F4+G4 -> 164720
B5: 2312 | C5: Desktop | D5: Dell | E5: 500000 | F5: =E5*11% -> 55000 | G5: =E5*5% -> 25000 | H5: =IF(E5>300000,"Nuevo","De Segunda") -> Nuevo | I5: =E5+F5+G5 -> 580000
B6: 2405 | C6: Plancha | D6: Mabe | E6: 20000 | F6: =E6*11% -> 2200 | G6: =E6*5% -> 1000 | H6: =IF(E6>300000,"Nuevo","De Segunda") -> De Segunda | I6: =E6+F6+G6 -> 23200
B7: 1112 | C7: Laptop | D7: Microsoft | E7: 1500000 | F7: =E7*11% -> 165000 | G7: =E7*5% -> 75000 | H7: =IF(E7>300000,"Nuevo","De Segunda") -> Nuevo | I7: =E7+F7+G7 -> 1740000
B8: 9875 | C8: Celular | D8: LG | E8: 50000 | F8: =E8*11% -> 5500 | G8: =E8*5% -> 2500 | H8: =IF(E8>300000,"Nuevo","De Segunda") -> De Segunda | I8: =E8+F8+G8 -> 58000
B9: 2306 | C9: Audifonos | D9: iPhone | E9: 68000 | F9: =E9*11% -> 7480 | G9: =E9*5% -> 3400 | H9: =IF(E9>300000,"Nuevo","De Segunda") -> De Segunda | I9: =E9+F9+G9 -> 78880
B10: 1911 | C10: Monitor | D10: Aoc | E10: 175000 | F10: =E10*11% -> 19250 | G10: =E10*5% -> 8750 | H10: =IF(E10>300000,"Nuevo","De Segunda") -> De Segunda | I10: =E10+F10+G10 -> 203000
B11: 8745 | C11: Tablet | D11: China | E11: 5000 | F11: =E11*11% -> 550 | G11: =E11*5% -> 250 | H11: =IF(E11>300000,"Nuevo","De Segunda") -> De Segunda | I11: =E11+F11+G11 -> 5800
B12: 1212 | C12: Refrigerador | D12: Mabe | E12: 548000 | F12: =E12*11% -> 60280 | G12: =E12*5% -> 27400 | H12: =IF(E12>300000,"Nuevo","De Segunda") -> Nuevo | I12: =E12+F12+G12 -> 635680

Sheet Busqueda
B2: Código | C2: 1121
B3: Articulo | C3: =LOOKUP(C2,Productos!$B$3:$B$12,Productos!$C$3:$C$12) -> Laptop
B4: Marca | C4: =LOOKUP(C2,Productos!$B$3:$B$12,Productos!$D$3:$D$12) -> Microsoft | D4: Aranceles | E4: =LOOKUP(C2,Productos!$B$3:$B$12,Productos!$F$3:$F$12) -> 165000
B5: Precio Compra | C5: =LOOKUP(C2,Productos!$B$3:$B$12,Productos!$E$3:$E$12) -> 1500000 | D5: Imp.Nacional | E5: =LOOKUP(Busqueda!C2,Productos!$B$3:$B$12,Productos!$G$3:$G$12) -> 75000
B6: Imp Servicio 3% | C6: =E7*3% -> 52200 | D6: Categoria | E6: =LOOKUP(C2,Productos!$B$3:$B$12,Productos!$H$3:$H$12) -> Nuevo
B7: I.V.A 4% | C7: =E7*4% -> 69600 | D7: Precio Venta | E7: =LOOKUP(C2,Productos!$B$3:$B$12,Productos!$I$3:$I$12) -> 1740000
B8: Total | C8: =E7+C6+C7 -> 1861800
